grai_source_bigquery/__init__.py
grai_source_bigquery/adapters.py
grai_source_bigquery/base.py
grai_source_bigquery/loader.py
grai_source_bigquery/models.py
grai_source_bigquery/package_definitions.py
grai_source_bigquery-0.2.4.dist-info/METADATA
grai_source_bigquery-0.2.4.dist-info/WHEEL
grai_source_bigquery-0.2.4.dist-info/RECORD
