Metadata-Version: 2.1
Name: grai_source_bigquery
Version: 0.2.4
Summary: 
Home-page: https://www.grai.io/
License: Elastic-2.0
Author: Edward Louth
Author-email: edward@grai.io
Requires-Python: >=3.8,<4.0
Classifier: License :: Other/Proprietary License
Classifier: Programming Language :: Python :: 3
Classifier: Programming Language :: Python :: 3.8
Classifier: Programming Language :: Python :: 3.9
Classifier: Programming Language :: Python :: 3.10
Classifier: Programming Language :: Python :: 3.11
Requires-Dist: google-cloud-bigquery (>=3.5.0,<4.0.0)
Requires-Dist: google-cloud-logging (>=3.5.0,<4.0.0)
Requires-Dist: grai-schemas (>=0.2.6,<0.3.0)
Requires-Dist: multimethod (>=1.8,<2.0)
Requires-Dist: pydantic (>=1.9.1,<2.0.0)
Requires-Dist: setuptools (>=67.1.0,<68.0.0)
Project-URL: Documentation, https://docs.grai.io/
Project-URL: Repository, https://github.com/grai-io/grai-core/tree/master/grai-integrations/source-bigquery
